conx/__init__.py
conx/_version.py
conx/activations.py
conx/dataset.py
conx/layers.py
conx/network.py
conx/utils.py
conx/widgets.py
conx/datasets/__init__.py
conx/datasets/_cifar10.py
conx/datasets/_cifar100.py
conx/datasets/_colors.py
conx/datasets/_fingers.py
conx/datasets/_gridfonts.py
conx/datasets/_mnist.py
conx/datasets/cmu_faces.py
conx/networks/__init__.py
conx/networks/_keras.py
conx-3.7.10.dist-info/LICENSE
conx-3.7.10.dist-info/METADATA
conx-3.7.10.dist-info/WHEEL
conx-3.7.10.dist-info/top_level.txt
conx-3.7.10.dist-info/RECORD
