Metadata-Version: 2.1
Name: conx
Version: 3.7.10
Summary: On-Ramp to Deep Learning. Built on Keras
Home-page: https://github.com/Calysto/conx
Author: Douglas S. Blank
Author-email: doug.blank@gmail.com
License: UNKNOWN
Platform: UNKNOWN
Classifier: Framework :: IPython
Classifier: License :: OSI Approved :: GNU Affero General Public License v3 or later (AGPLv3+)
Classifier: Programming Language :: Python :: 3
Requires-Dist: numpy
Requires-Dist: keras (>=2.1.3)
Requires-Dist: matplotlib
Requires-Dist: ipywidgets (>=7.0)
Requires-Dist: Pillow
Requires-Dist: IPython
Requires-Dist: h5py
Requires-Dist: svgwrite
Requires-Dist: sklearn
Requires-Dist: tqdm
Requires-Dist: requests
Requires-Dist: pydot
Requires-Dist: cairosvg
